<?xml version="1.0" encoding="utf-8"?>
<an:akomaNtoso xmlns:an="http://docs.oasis-open.org/legaldocml/ns/akn/3.0/CSD03" xmlns:auto-ns1="http://www.w3.org/2001/XMLSchema-instance" auto-ns1:schemaLocation="http://docs.oasis-open.org/legaldocml/ns/akn/3.0/CSD03 ../../Akoma/3.0/akomantoso30.xsd">
	<an:amendment contains="originalVersion">
		<an:meta>
			<an:identification xmlns="http://docs.oasis-open.org/legaldocml/ns/akn/3.0/CSD03" source="#redattore">
				<an:FRBRWork>
					<an:FRBRthis value="http://dati.senato.it/17/Emend/S/2860/A/8.0.2/main"/>
					<an:FRBRuri value="http://dati.senato.it/17/Emend/S/2860/A/8.0.2"/>
					<an:FRBRdate date="2017-07-26" name="presentazione"/>
					<an:FRBRauthor href="#senato"/>
					<an:componentInfo>
						<an:componentData id="wcompmain" href="http://dati.senato.it/17/Emend/S/2860/A/8.0.2/main" showAs="emendamento" name="emendamento"/>
					</an:componentInfo>
					<an:FRBRcountry value="ita"/>
					<an:FRBRsubtype value="EMEND"/>
					<an:FRBRnumber value="8.0.2"/>
					<an:FRBRname value="Emendamento"/>
				</an:FRBRWork>
				<an:FRBRExpression>
					<an:FRBRthis value="http://dati.senato.it/17/Emend/S/2860/A/8.0.2/ita@/main"/>
					<an:FRBRuri value="http://dati.senato.it/17/Emend/S/2860/A/8.0.2/ita@"/>
					<an:FRBRdate date="2017-07-26" name="presentazione"/>
					<an:FRBRauthor href="#senato"/>
					<an:componentInfo>
						<an:componentData id="ecompmain" href="http://dati.senato.it/17/Emend/S/2860/A/8.0.2/ita@/main" showAs="emendamento" name="emendamento"/>
					</an:componentInfo>
					<an:FRBRlanguage language="it"/>
				</an:FRBRExpression>
				<an:FRBRManifestation>
					<an:FRBRthis value="http://dati.senato.it/17/Emend/S/2860/A/8.0.2/ita@/main.xml"/>
					<an:FRBRuri value="http://dati.senato.it/17/Emend/S/2860/A/8.0.2/ita@.akn"/>
					<an:FRBRdate date="2017-07-26" name="presentazione"/>
					<an:FRBRauthor href="#redattore"/>
					<an:componentInfo>
						<an:componentData id="mcompmain" href="http://dati.senato.it/17/Emend/S/2860/A/8.0.2/ita@/main.xml" showAs="emendamento" name="emendamento"/>
					</an:componentInfo>
				</an:FRBRManifestation>
			</an:identification>
			<an:lifecycle source="#redattore">
				<an:eventRef source="#ro1" id="event1" date="2017-07-26"/>
			</an:lifecycle>
			<an:workflow source="#redattore">
				<an:step id="step1" date="2017-07-26" actor="#senato" outcome="presentazione"/>
			</an:workflow>
			<an:references source="#redattore">
				<an:original id="ro1" href="http://dati.senato.it/17/Emend/S/2860/A/8.0.2/ita@/main" showAs="generation"/>
				<an:activeRef id="ar1" href="http://dati.senato.it/DDL/17/2860" showAs="DDL 2860"/>
				<an:TLCOrganization id="redattore" showAs="Servizio Informatica del Senato della Repubblica" href="/dati.senato.it/osr/Senato/Servizio Informatica"/>
				<an:TLCOrganization id="senato" showAs="Senato della Repubblica" href="/dati.senato.it/osr/Senato"/>
				<an:TLCOrganization id="camera" showAs="Camera dei Deputati" href="/dati.senato.it/osr/Camera"/>
				<an:TLCRole id="tipoSenatore" href="http://dati.senato.it/Senatore" showAs="Senatore"/>
				<an:TLCPerson id="IDNRRBCMBGQAIAHNL4YJNU2OSO1BULYZGJKEJXBHNZFEFZ3RCDLTNL" href="http://dati.senato.it/29175" showAs="SANTINI"/>
				<an:TLCPerson id="ID12BEZKO3DMU1ZZTZDJIM1XGXLMOAT04X3NEI5JIIZYLXWLKEH2H" href="http://dati.senato.it/25226" showAs="BERTUZZI"/>
			</an:references>
		</an:meta>
		<an:preface>
			<an:p>
				<an:affectedDocument href="#ar1">DDL 2860</an:affectedDocument>
			</an:p>
			<an:p>
				<an:docNumber>Emendamento n. 8.0.2</an:docNumber>
			</an:p>
			<an:p>
				<an:docProponent refersTo="#IDNRRBCMBGQAIAHNL4YJNU2OSO1BULYZGJKEJXBHNZFEFZ3RCDLTNL" as="#tipoSenatore">SANTINI</an:docProponent>
			</an:p>
			<an:p>
				<an:docProponent refersTo="#ID12BEZKO3DMU1ZZTZDJIM1XGXLMOAT04X3NEI5JIIZYLXWLKEH2H" as="#tipoSenatore">BERTUZZI</an:docProponent>
			</an:p>
		</an:preface>
		<an:amendmentBody>
			<an:amendmentContent>
				<an:p>Dopo l'articolo inserire il seguente:</an:p>
				<an:p align="center">
					«Art. 8-
					<an:i>bis.</an:i>
				</an:p>
				<an:p align="center">
					<an:i>(Attuazione della Direttiva 2009/28/CE del Parlamento europeo e del consiglio del 23 aprile 2009 sulla promozione dell'uso dell'energia da fonti rinnovabili)</an:i>
				</an:p>
				<an:p>
					        1. All'articolo 2, comma 1, del decreto legislativo 3 marzo 2011 n. 28, dopo la lettera 
					<an:i>q-decies)</an:i>
					 è aggiunta la seguente:
				</an:p>
				<an:p>
					        &quot;
					<an:i>q-undecies)</an:i>
					 'soggetti auto-produttori': a tutti gli effetti di legge si intendono le imprese che producono l'energia elettrica con un proprio impianto e che la consumano esse stesse (totalmente o in parte, con cessione alla rete), compresi i consorzi e le società consortili costituiti per la produzione di energia elettrica da fonti energetiche rinnovabili utilizzata per uso proprio, per uso delle imprese ad esse associate e dei loro soci.&quot;».
				</an:p>
			</an:amendmentContent>
		</an:amendmentBody>
	</an:amendment>
</an:akomaNtoso>
