<?xml version="1.0" encoding="utf-8"?>
<an:akomaNtoso xmlns:an="http://docs.oasis-open.org/legaldocml/ns/akn/3.0/CSD03" xmlns:xp_0="http://www.w3.org/2001/XMLSchema-instance" xp_0:schemaLocation="http://docs.oasis-open.org/legaldocml/ns/akn/3.0/CSD03 ../../Akoma/3.0/akomantoso30.xsd">
	<an:amendment contains="originalVersion">
		<an:meta>
			<an:identification source="#redattore" xmlns="http://docs.oasis-open.org/legaldocml/ns/akn/3.0/CSD03">
				<an:FRBRWork>
					<an:FRBRthis value="http://dati.senato.it/16/Emend/S/2887/C/2.18/main"/>
					<an:FRBRuri value="http://dati.senato.it/16/Emend/S/2887/C/2.18"/>
					<an:FRBRdate date="2011-09-08" name="presentazione"/>
					<an:FRBRauthor href="#senato"/>
					<an:componentInfo>
						<an:componentData href="http://dati.senato.it/16/Emend/S/2887/C/2.18/main" id="wcompmain" name="emendamento" showAs="emendamento"/>
					</an:componentInfo>
					<an:FRBRcountry value="ita"/>
					<an:FRBRsubtype value="EMEND"/>
					<an:FRBRnumber value="2.18"/>
					<an:FRBRname value="Emendamento"/>
				</an:FRBRWork>
				<an:FRBRExpression>
					<an:FRBRthis value="http://dati.senato.it/16/Emend/S/2887/C/2.18/ita@/main"/>
					<an:FRBRuri value="http://dati.senato.it/16/Emend/S/2887/C/2.18/ita@"/>
					<an:FRBRdate date="2011-09-08" name="presentazione"/>
					<an:FRBRauthor href="#senato"/>
					<an:componentInfo>
						<an:componentData href="http://dati.senato.it/16/Emend/S/2887/C/2.18/ita@/main" id="ecompmain" name="emendamento" showAs="emendamento"/>
					</an:componentInfo>
					<an:FRBRlanguage language="it"/>
				</an:FRBRExpression>
				<an:FRBRManifestation>
					<an:FRBRthis value="http://dati.senato.it/16/Emend/S/2887/C/2.18/ita@/main.xml"/>
					<an:FRBRuri value="http://dati.senato.it/16/Emend/S/2887/C/2.18/ita@.akn"/>
					<an:FRBRdate date="2011-09-08" name="presentazione"/>
					<an:FRBRauthor href="#redattore"/>
					<an:componentInfo>
						<an:componentData href="http://dati.senato.it/16/Emend/S/2887/C/2.18/ita@/main.xml" id="mcompmain" name="emendamento" showAs="emendamento"/>
					</an:componentInfo>
				</an:FRBRManifestation>
			</an:identification>
			<an:lifecycle source="#redattore">
				<an:eventRef date="2011-09-08" id="event1" source="#ro1"/>
			</an:lifecycle>
			<an:workflow source="#redattore">
				<an:step actor="#senato" date="2011-09-08" id="step1" outcome="presentazione"/>
			</an:workflow>
			<an:references source="#redattore">
				<an:original href="http://dati.senato.it/16/Emend/S/2887/C/2.18/ita@/main" id="ro1" showAs="generation"/>
				<an:activeRef href="http://dati.senato.it/DDL/16/2887" id="ar1" showAs="DDL 2887"/>
				<an:TLCOrganization href="/dati.senato.it/osr/Senato/Servizio Informatica" id="redattore" showAs="Servizio Informatica del Senato della Repubblica"/>
				<an:TLCOrganization href="/dati.senato.it/osr/Senato" id="senato" showAs="Senato della Repubblica"/>
				<an:TLCOrganization href="/dati.senato.it/osr/Camera" id="camera" showAs="Camera dei Deputati"/>
				<an:TLCOrganization href="/dati.senato.it/osr/Commissione/5" id="commissione" showAs="Bilancio"/>
				<an:TLCRole href="http://dati.senato.it/Senatore" id="tipoSenatore" showAs="Senatore"/>
				<an:TLCPerson href="http://dati.senato.it/senatore/23254" id="EAB" showAs="Li Gotti"/>
				<an:TLCPerson href="http://dati.senato.it/senatore/25240" id="EFB" showAs="Mascitelli"/>
				<an:TLCPerson href="http://dati.senato.it/senatore/22864" id="EKB" showAs="Belisario"/>
				<an:TLCPerson href="http://dati.senato.it/senatore/22750" id="EPB" showAs="Giambrone"/>
				<an:TLCPerson href="http://dati.senato.it/senatore/25197" id="EUB" showAs="Bugnano"/>
				<an:TLCPerson href="http://dati.senato.it/senatore/22722" id="EZB" showAs="Caforio"/>
				<an:TLCPerson href="http://dati.senato.it/senatore/25202" id="E5B" showAs="Carlino"/>
				<an:TLCPerson href="http://dati.senato.it/senatore/25294" id="EDC" showAs="De Toni"/>
				<an:TLCPerson href="http://dati.senato.it/senatore/4414" id="EIC" showAs="Di Nardo"/>
				<an:TLCPerson href="http://dati.senato.it/senatore/17211" id="ENC" showAs="Lannutti"/>
				<an:TLCPerson href="http://dati.senato.it/senatore/25227" id="ESC" showAs="Pardi"/>
				<an:TLCPerson href="http://dati.senato.it/senatore/12480" id="EXC" showAs="Pedica"/>
			</an:references>
		</an:meta>
		<an:preface>
			<an:p>
				<an:affectedDocument href="#ar1">DDL 2887</an:affectedDocument>
			</an:p>
			<an:p>
				<an:docNumber>Emendamento n. 2.18</an:docNumber>
			</an:p>
			<an:p>
				<an:docProponent as="#tipoSenatore" refersTo="#EAB">Li Gotti</an:docProponent>
			</an:p>
			<an:p>
				<an:docProponent as="#tipoSenatore" refersTo="#EFB">Mascitelli</an:docProponent>
			</an:p>
			<an:p>
				<an:docProponent as="#tipoSenatore" refersTo="#EKB">Belisario</an:docProponent>
			</an:p>
			<an:p>
				<an:docProponent as="#tipoSenatore" refersTo="#EPB">Giambrone</an:docProponent>
			</an:p>
			<an:p>
				<an:docProponent as="#tipoSenatore" refersTo="#EUB">Bugnano</an:docProponent>
			</an:p>
			<an:p>
				<an:docProponent as="#tipoSenatore" refersTo="#EZB">Caforio</an:docProponent>
			</an:p>
			<an:p>
				<an:docProponent as="#tipoSenatore" refersTo="#E5B">Carlino</an:docProponent>
			</an:p>
			<an:p>
				<an:docProponent as="#tipoSenatore" refersTo="#EDC">De Toni</an:docProponent>
			</an:p>
			<an:p>
				<an:docProponent as="#tipoSenatore" refersTo="#EIC">Di Nardo</an:docProponent>
			</an:p>
			<an:p>
				<an:docProponent as="#tipoSenatore" refersTo="#ENC">Lannutti</an:docProponent>
			</an:p>
			<an:p>
				<an:docProponent as="#tipoSenatore" refersTo="#ESC">Pardi</an:docProponent>
			</an:p>
			<an:p>
				<an:docProponent as="#tipoSenatore" refersTo="#EXC">Pedica</an:docProponent>
			</an:p>
		</an:preface>
		<an:amendmentBody>
			<an:amendmentContent>
				<an:p>
					<an:i>Sostituire il comma 3 con i seguenti:</an:i>
				</an:p>
				<an:p>        «3. A decorrere dal 1 giugno 2011, il prelievo erariale unico di cui all'articolo 39, comma 13, del decreto-legge 30 settembre 2003, n. 269, convertito, con modificazioni, dalla legge 24 novembre 2003, n. 326, e successive modificazioni. è determinato, in capo ai singoli soggetti passivi d'imposta, applicando un'aliquota pari al 20 per cento.</an:p>
				<an:p>
					        3-
					<an:i>bis</an:i>
					. Fermo quanto disposto dall'articolo 39, comma 13-
					<an:i>bis</an:i>
					, del decreto-legge 30 settembre 2003, n. 269, convertito, con modificazioni, dalla legge 24 novembre 2003. n. 326, e successive modificazioni, e dai relativi decreti direttoriali di applicazione, gli importi dei versamenti periodici del prelievo erariale unico dovuti dai soggetti passivi di imposta in relazione ai singoli periodi contabili sono calcolati assumendo un'aliquota pari al 98 per cento di quella prevista dal comma 1.
				</an:p>
				<an:p>
					        3-
					<an:i>ter</an:i>
					. Il Direttore generale dell'Amministrazione autonoma dei monopoli di Stato può proporre al Ministro dell'economia e delle finanze di disporre con propri decreti, entro il 31 dicembre 2011, tenuto anche conto dei provvedimenti di variazione delle tariffe dei prezzi di vendita al pubblico dei tabacchi lavorati eventualmente intervenuti, l'aumento dell'aliquota di base dell'imposta di consumo sulle sigarette prevista dall'allegato I al decreto legislativo 26 ottobre 1995, n. 504 e successive modificazioni. L'attuazione delle disposizioni del presente comma assicura maggiori entrate in misura non inferiore a 1.500 milioni di euro annui a decorrere dall'anno 2012. Le maggiori entrate derivanti dal presente comma sono integralmente attribuite allo Stato.
				</an:p>
				<an:p>
					        3-
					<an:i>quater</an:i>
					. Una quota non inferiore al 3 per cento del Prelievo Erariale Unico è destinata annualmente, dal Ministero dell'Economia e delle Finanze - Amministrazione autonoma dei Monopoli di Stato, all'attuazione di misure di contrasto al fenomeni di ludopatia connessi al gioco.»
				</an:p>
			</an:amendmentContent>
		</an:amendmentBody>
	</an:amendment>
</an:akomaNtoso>
