<?xml version="1.0" encoding="utf-8"?>
<an:akomaNtoso xmlns:an="http://docs.oasis-open.org/legaldocml/ns/akn/3.0/CSD03" xmlns:auto-ns1="http://www.w3.org/2001/XMLSchema-instance" auto-ns1:schemaLocation="http://docs.oasis-open.org/legaldocml/ns/akn/3.0/CSD03 ../../Akoma/3.0/akomantoso30.xsd">
	<an:amendment contains="originalVersion">
		<an:meta>
			<an:identification xmlns="http://docs.oasis-open.org/legaldocml/ns/akn/3.0/CSD03" source="#redattore">
				<an:FRBRWork>
					<an:FRBRthis value="http://dati.senato.it/18/Emend/S/981/A/1.590/main"/>
					<an:FRBRuri value="http://dati.senato.it/18/Emend/S/981/A/1.590"/>
					<an:FRBRdate date="2018-12-23" name="presentazione"/>
					<an:FRBRauthor href="#senato"/>
					<an:componentInfo>
						<an:componentData id="wcompmain" href="http://dati.senato.it/18/Emend/S/981/A/1.590/main" showAs="emendamento" name="emendamento"/>
					</an:componentInfo>
					<an:FRBRcountry value="ita"/>
					<an:FRBRsubtype value="EMEND"/>
					<an:FRBRnumber value="1.590"/>
					<an:FRBRname value="Emendamento"/>
				</an:FRBRWork>
				<an:FRBRExpression>
					<an:FRBRthis value="http://dati.senato.it/18/Emend/S/981/A/1.590/ita@/main"/>
					<an:FRBRuri value="http://dati.senato.it/18/Emend/S/981/A/1.590/ita@"/>
					<an:FRBRdate date="2018-12-23" name="presentazione"/>
					<an:FRBRauthor href="#senato"/>
					<an:componentInfo>
						<an:componentData id="ecompmain" href="http://dati.senato.it/18/Emend/S/981/A/1.590/ita@/main" showAs="emendamento" name="emendamento"/>
					</an:componentInfo>
					<an:FRBRlanguage language="it"/>
				</an:FRBRExpression>
				<an:FRBRManifestation>
					<an:FRBRthis value="http://dati.senato.it/18/Emend/S/981/A/1.590/ita@/main.xml"/>
					<an:FRBRuri value="http://dati.senato.it/18/Emend/S/981/A/1.590/ita@.akn"/>
					<an:FRBRdate date="2018-12-23" name="presentazione"/>
					<an:FRBRauthor href="#redattore"/>
					<an:componentInfo>
						<an:componentData id="mcompmain" href="http://dati.senato.it/18/Emend/S/981/A/1.590/ita@/main.xml" showAs="emendamento" name="emendamento"/>
					</an:componentInfo>
				</an:FRBRManifestation>
			</an:identification>
			<an:lifecycle source="#redattore">
				<an:eventRef source="#ro1" id="event1" date="2018-12-23"/>
			</an:lifecycle>
			<an:workflow source="#redattore">
				<an:step id="step1" date="2018-12-23" actor="#senato" outcome="presentazione"/>
			</an:workflow>
			<an:references source="#redattore">
				<an:original id="ro1" href="http://dati.senato.it/18/Emend/S/981/A/1.590/ita@/main" showAs="generation"/>
				<an:activeRef id="ar1" href="http://dati.senato.it/DDL/18/981" showAs="DDL 981"/>
				<an:TLCOrganization id="redattore" showAs="Servizio Informatica del Senato della Repubblica" href="/dati.senato.it/osr/Senato/Servizio Informatica"/>
				<an:TLCOrganization id="senato" showAs="Senato della Repubblica" href="/dati.senato.it/osr/Senato"/>
				<an:TLCOrganization id="camera" showAs="Camera dei Deputati" href="/dati.senato.it/osr/Camera"/>
				<an:TLCRole id="tipoSenatore" href="http://dati.senato.it/Senatore" showAs="Senatore"/>
				<an:TLCPerson id="IDA2KV30MIVNRDBOP3HQHHLGQGUIJD3EN0WN0CQRKDRIPFAJM42SOI" href="http://dati.senato.it/32726" showAs="TURCO"/>
				<an:TLCPerson id="IDRXTYT3OFMT0LIVKQD1HHCGCBPEWWQXQTY24LVBEMDNMT44WTAK1G" href="http://dati.senato.it/32691" showAs="PIRRO"/>
				<an:TLCPerson id="IDPKJUBLGC3XQZKA4M315PZB31WMLCHJ1H3RJYDOCKM2VWK4P30AEH" href="http://dati.senato.it/32684" showAs="Marco PELLEGRINI"/>
				<an:TLCPerson id="IDUWKVSDJMYJV5HU0FLQOKDH4YUFHHIFZ0QXRR1ICKXQPNF3ETGYBN" href="http://dati.senato.it/32696" showAs="PRESUTTO"/>
				<an:TLCPerson id="IDPJSKTNVWDI5QFCJPKUKEMU4ILJHFQ1E5DY0NKP4NJYFTJB1CBTN" href="http://dati.senato.it/32638" showAs="GALLICCHIO"/>
				<an:TLCPerson id="IDN0NOFJSMLGAUFGFSJE4WK1BECP02WFRTVQZXVFBJWT0OJMBPQKYF" href="http://dati.senato.it/32577" showAs="ACCOTO"/>
				<an:TLCPerson id="ID5KY1BVCFMHD4DC43UDSAIBXJ1GIPQVOUZ1NQ4INHLCA0VNQTX5CP" href="http://dati.senato.it/29527" showAs="PESCO"/>
				<an:TLCPerson id="IDLD4C4VDVZ25HJSPEMCGED3IUEBDIXXKMIHBO0DJYURBU1H3M03GD" href="http://dati.senato.it/32681" showAs="PATUANELLI"/>
			</an:references>
		</an:meta>
		<an:preface>
			<an:p>
				<an:affectedDocument href="#ar1">DDL 981</an:affectedDocument>
			</an:p>
			<an:p>
				<an:docNumber>Emendamento n. 1.590</an:docNumber>
			</an:p>
			<an:p>
				<an:docProponent refersTo="#IDA2KV30MIVNRDBOP3HQHHLGQGUIJD3EN0WN0CQRKDRIPFAJM42SOI" as="#tipoSenatore">TURCO</an:docProponent>
			</an:p>
			<an:p>
				<an:docProponent refersTo="#IDRXTYT3OFMT0LIVKQD1HHCGCBPEWWQXQTY24LVBEMDNMT44WTAK1G" as="#tipoSenatore">PIRRO</an:docProponent>
			</an:p>
			<an:p>
				<an:docProponent refersTo="#IDPKJUBLGC3XQZKA4M315PZB31WMLCHJ1H3RJYDOCKM2VWK4P30AEH" as="#tipoSenatore">Marco PELLEGRINI</an:docProponent>
			</an:p>
			<an:p>
				<an:docProponent refersTo="#IDUWKVSDJMYJV5HU0FLQOKDH4YUFHHIFZ0QXRR1ICKXQPNF3ETGYBN" as="#tipoSenatore">PRESUTTO</an:docProponent>
			</an:p>
			<an:p>
				<an:docProponent refersTo="#IDPJSKTNVWDI5QFCJPKUKEMU4ILJHFQ1E5DY0NKP4NJYFTJB1CBTN" as="#tipoSenatore">GALLICCHIO</an:docProponent>
			</an:p>
			<an:p>
				<an:docProponent refersTo="#IDN0NOFJSMLGAUFGFSJE4WK1BECP02WFRTVQZXVFBJWT0OJMBPQKYF" as="#tipoSenatore">ACCOTO</an:docProponent>
			</an:p>
			<an:p>
				<an:docProponent refersTo="#ID5KY1BVCFMHD4DC43UDSAIBXJ1GIPQVOUZ1NQ4INHLCA0VNQTX5CP" as="#tipoSenatore">PESCO</an:docProponent>
			</an:p>
			<an:p>
				<an:docProponent refersTo="#IDLD4C4VDVZ25HJSPEMCGED3IUEBDIXXKMIHBO0DJYURBU1H3M03GD" as="#tipoSenatore">PATUANELLI</an:docProponent>
			</an:p>
		</an:preface>
		<an:amendmentBody>
			<an:amendmentContent>
				<an:p>
					<an:i>Dopo il comma 60, aggiungere il seguente</an:i>
					:
				</an:p>
				<an:p>
					        «60-
					<an:i>bis</an:i>
					. Per i Programmi (PRiU) di cui al decreto del Ministro delle infrastrutture e dei trasporti del 9 settembre 2015, nel caso di interruzione delle attività di cantiere determinata da eventi indipendenti dalla volontà delle parti contraenti (forza maggiore), tutti i termini dell'articolo 1 dello stesso decreto ministeriale si intendono comunque prorogati del tempo di &quot;fermo cantiere&quot;, così come riconosciuto dal Collegio di Vigilanza. Per &quot;opere pubbliche avviate» devono intendersi quelle per le quali sia stata avviata la progettazione definitiva secondo legislazione sui lavori pubblici, per «opere private avviate&quot; devono intendersi quelle per le quali sia stata presentata all'ufficio competente istanza di Permesso di Costruire o atto equivalente. Resta ferma la facoltà del Collegio di Vigilanza di modificare il cronoprogramma.».
				</an:p>
			</an:amendmentContent>
		</an:amendmentBody>
	</an:amendment>
</an:akomaNtoso>
