<?xml version="1.0" encoding="utf-8"?>
<an:akomaNtoso xmlns:an="http://docs.oasis-open.org/legaldocml/ns/akn/3.0/CSD03" xmlns:auto-ns1="http://www.w3.org/2001/XMLSchema-instance" auto-ns1:schemaLocation="http://docs.oasis-open.org/legaldocml/ns/akn/3.0/CSD03 ../../Akoma/3.0/akomantoso30.xsd">
	<an:amendment contains="originalVersion">
		<an:meta>
			<an:identification xmlns="http://docs.oasis-open.org/legaldocml/ns/akn/3.0/CSD03" source="#redattore">
				<an:FRBRWork>
					<an:FRBRthis value="http://dati.senato.it/18/Emend/S/1631/A/3-bis.7/main"/>
					<an:FRBRuri value="http://dati.senato.it/18/Emend/S/1631/A/3-bis.7"/>
					<an:FRBRdate date="2019-12-11" name="presentazione"/>
					<an:FRBRauthor href="#senato"/>
					<an:componentInfo>
						<an:componentData id="wcompmain" href="http://dati.senato.it/18/Emend/S/1631/A/3-bis.7/main" showAs="emendamento" name="emendamento"/>
					</an:componentInfo>
					<an:FRBRcountry value="ita"/>
					<an:FRBRsubtype value="EMEND"/>
					<an:FRBRnumber value="3-bis.7"/>
					<an:FRBRname value="Emendamento"/>
				</an:FRBRWork>
				<an:FRBRExpression>
					<an:FRBRthis value="http://dati.senato.it/18/Emend/S/1631/A/3-bis.7/ita@/main"/>
					<an:FRBRuri value="http://dati.senato.it/18/Emend/S/1631/A/3-bis.7/ita@"/>
					<an:FRBRdate date="2019-12-11" name="presentazione"/>
					<an:FRBRauthor href="#senato"/>
					<an:componentInfo>
						<an:componentData id="ecompmain" href="http://dati.senato.it/18/Emend/S/1631/A/3-bis.7/ita@/main" showAs="emendamento" name="emendamento"/>
					</an:componentInfo>
					<an:FRBRlanguage language="it"/>
				</an:FRBRExpression>
				<an:FRBRManifestation>
					<an:FRBRthis value="http://dati.senato.it/18/Emend/S/1631/A/3-bis.7/ita@/main.xml"/>
					<an:FRBRuri value="http://dati.senato.it/18/Emend/S/1631/A/3-bis.7/ita@.akn"/>
					<an:FRBRdate date="2019-12-11" name="presentazione"/>
					<an:FRBRauthor href="#redattore"/>
					<an:componentInfo>
						<an:componentData id="mcompmain" href="http://dati.senato.it/18/Emend/S/1631/A/3-bis.7/ita@/main.xml" showAs="emendamento" name="emendamento"/>
					</an:componentInfo>
				</an:FRBRManifestation>
			</an:identification>
			<an:lifecycle source="#redattore">
				<an:eventRef source="#ro1" id="event1" date="2019-12-11"/>
			</an:lifecycle>
			<an:workflow source="#redattore">
				<an:step id="step1" date="2019-12-11" actor="#senato" outcome="presentazione"/>
			</an:workflow>
			<an:references source="#redattore">
				<an:original id="ro1" href="http://dati.senato.it/18/Emend/S/1631/A/3-bis.7/ita@/main" showAs="generation"/>
				<an:activeRef id="ar1" href="http://dati.senato.it/DDL/18/1631" showAs="DDL 1631"/>
				<an:TLCOrganization id="redattore" showAs="Servizio Informatica del Senato della Repubblica" href="/dati.senato.it/osr/Senato/Servizio Informatica"/>
				<an:TLCOrganization id="senato" showAs="Senato della Repubblica" href="/dati.senato.it/osr/Senato"/>
				<an:TLCOrganization id="camera" showAs="Camera dei Deputati" href="/dati.senato.it/osr/Camera"/>
				<an:TLCRole id="tipoSenatore" href="http://dati.senato.it/Senatore" showAs="Senatore"/>
				<an:TLCPerson id="IDL5QMR33FFHOBPZIXLCL2TXBWPWLOQP3PJG55ULCA2KKYCTEZGXG" href="http://dati.senato.it/32679" showAs="PAGANO"/>
				<an:TLCPerson id="IDCZOYBSBDV51QMSLEYO1M21XBYDZX1WTAB5YT2TIWDRQHWB3WR5MB" href="http://dati.senato.it/32597" showAs="CANGINI"/>
				<an:TLCPerson id="ID1QPFW4RADZNLME4I0W2ZBKWNTSPHS2RTJ1JM2M2AWH2MG54ERMO" href="http://dati.senato.it/32671" showAs="MODENA"/>
				<an:TLCPerson id="IDSVD0XEJXPQW3EHWRWXFP0FE5LH0Z5ENRXF4QUFHWVZSEOX42OLUO" href="http://dati.senato.it/32741" showAs="AIMI"/>
				<an:TLCPerson id="IDCSI3OIFVZJ5SNI0OO00H0XQEPMIYEZMSNJVZQ5KP5JGDLXXOAOJI" href="http://dati.senato.it/32584" showAs="BARBONI"/>
				<an:TLCPerson id="IDZYXGKMAQKJAGMSINOPIRTMMNAILPIJUF0PKOIRKZTIZFL2ESHHSB" href="http://dati.senato.it/4192" showAs="FAZZONE"/>
				<an:TLCPerson id="IDH0CX14OGX5S0FY3QEVSQOIZEWD3QUYTKJYP2HKHLPSGDWSCE3ZOJ" href="http://dati.senato.it/24989" showAs="BATTISTONI"/>
				<an:TLCPerson id="ID0YW215OUR5PHB2D24IDQIE4JWP1M3PLY31QU5HCBGRVUAZ42NW" href="http://dati.senato.it/22970" showAs="GIRO"/>
			</an:references>
		</an:meta>
		<an:preface>
			<an:p>
				<an:affectedDocument href="#ar1">DDL 1631</an:affectedDocument>
			</an:p>
			<an:p>
				<an:docNumber>Emendamento n. 3-bis.7</an:docNumber>
			</an:p>
			<an:p>
				<an:docProponent refersTo="#IDL5QMR33FFHOBPZIXLCL2TXBWPWLOQP3PJG55ULCA2KKYCTEZGXG" as="#tipoSenatore">PAGANO</an:docProponent>
			</an:p>
			<an:p>
				<an:docProponent refersTo="#IDCZOYBSBDV51QMSLEYO1M21XBYDZX1WTAB5YT2TIWDRQHWB3WR5MB" as="#tipoSenatore">CANGINI</an:docProponent>
			</an:p>
			<an:p>
				<an:docProponent refersTo="#ID1QPFW4RADZNLME4I0W2ZBKWNTSPHS2RTJ1JM2M2AWH2MG54ERMO" as="#tipoSenatore">MODENA</an:docProponent>
			</an:p>
			<an:p>
				<an:docProponent refersTo="#IDSVD0XEJXPQW3EHWRWXFP0FE5LH0Z5ENRXF4QUFHWVZSEOX42OLUO" as="#tipoSenatore">AIMI</an:docProponent>
			</an:p>
			<an:p>
				<an:docProponent refersTo="#IDCSI3OIFVZJ5SNI0OO00H0XQEPMIYEZMSNJVZQ5KP5JGDLXXOAOJI" as="#tipoSenatore">BARBONI</an:docProponent>
			</an:p>
			<an:p>
				<an:docProponent refersTo="#IDZYXGKMAQKJAGMSINOPIRTMMNAILPIJUF0PKOIRKZTIZFL2ESHHSB" as="#tipoSenatore">FAZZONE</an:docProponent>
			</an:p>
			<an:p>
				<an:docProponent refersTo="#IDH0CX14OGX5S0FY3QEVSQOIZEWD3QUYTKJYP2HKHLPSGDWSCE3ZOJ" as="#tipoSenatore">BATTISTONI</an:docProponent>
			</an:p>
			<an:p>
				<an:docProponent refersTo="#ID0YW215OUR5PHB2D24IDQIE4JWP1M3PLY31QU5HCBGRVUAZ42NW" as="#tipoSenatore">GIRO</an:docProponent>
			</an:p>
		</an:preface>
		<an:amendmentBody>
			<an:amendmentContent>
				<an:p>
					<an:i>Al comma 2, primo periodo, dopo le parole:</an:i>
					 «Ufficio speciale per la ricostruzione,» 
					<an:i>aggiungere le seguenti:</an:i>
					 «anche ricorrendo alla collaborazione esterna finalizzata alla redazione dei medesimi Programmi,».
				</an:p>
			</an:amendmentContent>
		</an:amendmentBody>
	</an:amendment>
</an:akomaNtoso>
