<?xml version="1.0" encoding="utf-8"?>
<an:akomaNtoso auto-ns1:schemaLocation="http://docs.oasis-open.org/legaldocml/ns/akn/3.0/CSD03 ../../Akoma/3.0/akomantoso30.xsd" xmlns:an="http://docs.oasis-open.org/legaldocml/ns/akn/3.0/CSD03" xmlns:auto-ns1="http://www.w3.org/2001/XMLSchema-instance">
	<an:amendment contains="originalVersion">
		<an:meta>
			<an:identification source="#redattore" xmlns="http://docs.oasis-open.org/legaldocml/ns/akn/3.0/CSD03">
				<an:FRBRWork>
					<an:FRBRthis value="http://dati.senato.it/18/Emend/S/1883/A/8.16/main"/>
					<an:FRBRuri value="http://dati.senato.it/18/Emend/S/1883/A/8.16"/>
					<an:FRBRdate date="2020-09-16" name="presentazione"/>
					<an:FRBRauthor href="#senato"/>
					<an:componentInfo>
						<an:componentData href="http://dati.senato.it/18/Emend/S/1883/A/8.16/main" id="wcompmain" name="emendamento" showAs="emendamento"/>
					</an:componentInfo>
					<an:FRBRcountry value="ita"/>
					<an:FRBRsubtype value="EMEND"/>
					<an:FRBRnumber value="8.16"/>
					<an:FRBRname value="Emendamento"/>
				</an:FRBRWork>
				<an:FRBRExpression>
					<an:FRBRthis value="http://dati.senato.it/18/Emend/S/1883/A/8.16/ita@/main"/>
					<an:FRBRuri value="http://dati.senato.it/18/Emend/S/1883/A/8.16/ita@"/>
					<an:FRBRdate date="2020-09-16" name="presentazione"/>
					<an:FRBRauthor href="#senato"/>
					<an:componentInfo>
						<an:componentData href="http://dati.senato.it/18/Emend/S/1883/A/8.16/ita@/main" id="ecompmain" name="emendamento" showAs="emendamento"/>
					</an:componentInfo>
					<an:FRBRlanguage language="it"/>
				</an:FRBRExpression>
				<an:FRBRManifestation>
					<an:FRBRthis value="http://dati.senato.it/18/Emend/S/1883/A/8.16/ita@/main.xml"/>
					<an:FRBRuri value="http://dati.senato.it/18/Emend/S/1883/A/8.16/ita@.akn"/>
					<an:FRBRdate date="2020-09-16" name="presentazione"/>
					<an:FRBRauthor href="#redattore"/>
					<an:componentInfo>
						<an:componentData href="http://dati.senato.it/18/Emend/S/1883/A/8.16/ita@/main.xml" id="mcompmain" name="emendamento" showAs="emendamento"/>
					</an:componentInfo>
				</an:FRBRManifestation>
			</an:identification>
			<an:lifecycle source="#redattore">
				<an:eventRef date="2020-09-16" id="event1" source="#ro1"/>
			</an:lifecycle>
			<an:workflow source="#redattore">
				<an:step actor="#senato" date="2020-09-16" id="step1" outcome="presentazione"/>
			</an:workflow>
			<an:references source="#redattore">
				<an:original href="http://dati.senato.it/18/Emend/S/1883/A/8.16/ita@/main" id="ro1" showAs="generation"/>
				<an:activeRef href="http://dati.senato.it/DDL/18/1883" id="ar1" showAs="DDL 1883"/>
				<an:TLCOrganization href="/dati.senato.it/osr/Senato/Servizio Informatica" id="redattore" showAs="Servizio Informatica del Senato della Repubblica"/>
				<an:TLCOrganization href="/dati.senato.it/osr/Senato" id="senato" showAs="Senato della Repubblica"/>
				<an:TLCOrganization href="/dati.senato.it/osr/Camera" id="camera" showAs="Camera dei Deputati"/>
				<an:TLCRole href="http://dati.senato.it/Senatore" id="tipoSenatore" showAs="Senatore"/>
				<an:TLCPerson href="http://dati.senato.it/32659" id="ID2KRF4OE131OKNGEFXZHRG5EWSNKGZK42CYVLVLDUOBHFD0GLNW0B" showAs="MALLEGNI"/>
				<an:TLCPerson href="http://dati.senato.it/32679" id="IDXEHS43HOPZNBLUO0LLNZRIXIYNKC4EQSOJAE4KCNSR4AXVNSB" showAs="PAGANO"/>
				<an:TLCPerson href="http://dati.senato.it/4512" id="IDHH3JXYTRGLNJP5TLOED5DRW2OP1IYJGCBONIHGFJ44YXVH31XTDH" showAs="PAROLI"/>
				<an:TLCPerson href="http://dati.senato.it/4584" id="ID0LFAEJBFSKVRKIRFWKM2QBGLQJGSHQ3BGBDKQHORRDMN335CXSGE" showAs="VITALI"/>
				<an:TLCPerson href="http://dati.senato.it/32583" id="IDHS34A2SSQIIQJDVJOT2BSZRHNJN41HOJ5434CQLLHQYUC1SCZXDH" showAs="BARACHINI"/>
				<an:TLCPerson href="http://dati.senato.it/32584" id="IDRCEFVJPQHUAUJMWEXFA1WIPNBKGTJZV5AHDDHVCZKGNL3QCLKSYN" showAs="BARBONI"/>
				<an:TLCPerson href="http://dati.senato.it/4192" id="ID0W5RXBSLYF22BNWYEFFYMBZTLC4B1TQ2HEYHDHKZKRYVOFHEZQMD" showAs="FAZZONE"/>
				<an:TLCPerson href="http://dati.senato.it/3939" id="IDV1I54ZQGU1R0LR0CACVD24ENLFTHUFFQS40P5DY3DASNAODQAMP" showAs="SCHIFANI"/>
				<an:TLCPerson href="http://dati.senato.it/1103" id="ID3BLGUBHV2E5EOKKEUUMADCP51J0MDZGJCFTOBRLIT4APN3M1XYYP" showAs="GASPARRI"/>
				<an:TLCPerson href="http://dati.senato.it/32666" id="IDPSQSNZ05WNCRIMT1QUOQIEMFDJCGC2A5N1RS43FW1Y3WE1EGSBTF" showAs="MASINI"/>
				<an:TLCPerson href="http://dati.senato.it/32714" id="IDFGWERTG4AE0ZLIWYBUJLHAMYVCPGG5531KWFJNB0VXXXY1W3KAHL" showAs="SICLARI"/>
			</an:references>
		</an:meta>
		<an:preface>
			<an:p>
				<an:affectedDocument href="#ar1">DDL 1883</an:affectedDocument>
			</an:p>
			<an:p>
				<an:docNumber>Emendamento n. 8.16</an:docNumber>
			</an:p>
			<an:p>
				<an:docProponent as="#tipoSenatore" refersTo="#ID2KRF4OE131OKNGEFXZHRG5EWSNKGZK42CYVLVLDUOBHFD0GLNW0B">MALLEGNI</an:docProponent>
			</an:p>
			<an:p>
				<an:docProponent as="#tipoSenatore" refersTo="#IDXEHS43HOPZNBLUO0LLNZRIXIYNKC4EQSOJAE4KCNSR4AXVNSB">PAGANO</an:docProponent>
			</an:p>
			<an:p>
				<an:docProponent as="#tipoSenatore" refersTo="#IDHH3JXYTRGLNJP5TLOED5DRW2OP1IYJGCBONIHGFJ44YXVH31XTDH">PAROLI</an:docProponent>
			</an:p>
			<an:p>
				<an:docProponent as="#tipoSenatore" refersTo="#ID0LFAEJBFSKVRKIRFWKM2QBGLQJGSHQ3BGBDKQHORRDMN335CXSGE">VITALI</an:docProponent>
			</an:p>
			<an:p>
				<an:docProponent as="#tipoSenatore" refersTo="#IDHS34A2SSQIIQJDVJOT2BSZRHNJN41HOJ5434CQLLHQYUC1SCZXDH">BARACHINI</an:docProponent>
			</an:p>
			<an:p>
				<an:docProponent as="#tipoSenatore" refersTo="#IDRCEFVJPQHUAUJMWEXFA1WIPNBKGTJZV5AHDDHVCZKGNL3QCLKSYN">BARBONI</an:docProponent>
			</an:p>
			<an:p>
				<an:docProponent as="#tipoSenatore" refersTo="#ID0W5RXBSLYF22BNWYEFFYMBZTLC4B1TQ2HEYHDHKZKRYVOFHEZQMD">FAZZONE</an:docProponent>
			</an:p>
			<an:p>
				<an:docProponent as="#tipoSenatore" refersTo="#IDV1I54ZQGU1R0LR0CACVD24ENLFTHUFFQS40P5DY3DASNAODQAMP">SCHIFANI</an:docProponent>
			</an:p>
			<an:p>
				<an:docProponent as="#tipoSenatore" refersTo="#ID3BLGUBHV2E5EOKKEUUMADCP51J0MDZGJCFTOBRLIT4APN3M1XYYP">GASPARRI</an:docProponent>
			</an:p>
			<an:p>
				<an:docProponent as="#tipoSenatore" refersTo="#IDPSQSNZ05WNCRIMT1QUOQIEMFDJCGC2A5N1RS43FW1Y3WE1EGSBTF">MASINI</an:docProponent>
			</an:p>
			<an:p>
				<an:docProponent as="#tipoSenatore" refersTo="#IDFGWERTG4AE0ZLIWYBUJLHAMYVCPGG5531KWFJNB0VXXXY1W3KAHL">SICLARI</an:docProponent>
			</an:p>
		</an:preface>
		<an:amendmentBody>
			<an:amendmentContent>
				<an:p>
					<an:i>Al comma 4, lettera</an:i>
					 b)
					<an:i>, dopo le parole:</an:i>
					 «maggiori costi» 
					<an:i>inserire le seguenti:</an:i>
					 «nonché i maggiori oneri, diretti ed indiretti,», 
					<an:i>inoltre, dopo le parole:</an:i>
					 «il rimborso», 
					<an:i>sostituire le parole:</an:i>
					 «di detti oneri» 
					<an:i>con le seguenti:</an:i>
					 «dei costi».
				</an:p>
			</an:amendmentContent>
		</an:amendmentBody>
	</an:amendment>
</an:akomaNtoso>
